querpyable/__init__.py
querpyable/py.typed
querpyable/querpyable.py
querpyable-3.0.0.dist-info/LICENSE
querpyable-3.0.0.dist-info/METADATA
querpyable-3.0.0.dist-info/WHEEL
querpyable-3.0.0.dist-info/RECORD
