Metadata-Version: 2.1
Name: Querpyable
Version: 3.0.0
Summary: A Python implementation of LINQ
Home-page: https://billsioros.github.io/querpyable
License: MIT
Author: Vasilis Sioros
Author-email: billsioros97@gmail.com
Requires-Python: >=3.9,<4.0
Classifier: License :: OSI Approved :: MIT License
Classifier: Programming Language :: Python
Classifier: Programming Language :: Python :: 3
Classifier: Programming Language :: Python :: 3.9
Classifier: Programming Language :: Python :: 3.10
Classifier: Programming Language :: Python :: 3.11
Classifier: Programming Language :: Python :: 3.12
Classifier: Programming Language :: Python :: 3 :: Only
Project-URL: Bug Tracker, https://github.com/billsioros/querpyable/issues
Project-URL: Changelog, https://github.com/billsioros/querpyable/releases
Project-URL: Repository, https://github.com/billsioros/querpyable
